lektor_asciidoc.py
lektor_asciidoc-0.3.dist-info/METADATA
lektor_asciidoc-0.3.dist-info/RECORD
lektor_asciidoc-0.3.dist-info/WHEEL
lektor_asciidoc-0.3.dist-info/entry_points.txt
lektor_asciidoc-0.3.dist-info/top_level.txt
