Metadata-Version: 2.1
Name: lektor-asciidoc
Version: 0.3
Summary: Adds AsciiDoc field type to Lektor.
Home-page: https://github.com/nixjdm/lektor-asciidoc
Author: A. Jesse Jiryu Davis
Author-email: jesse@emptysquare.net
License: MIT
Keywords: Lektor plugin static-site blog asciidoc
Platform: UNKNOWN
Classifier: Environment :: Plugins
Classifier: Environment :: Web Environment
Classifier: Framework :: Lektor
Classifier: Intended Audience :: Developers
Classifier: License :: OSI Approved :: MIT License
